Metadata-Version: 2.3
Name: yt-dlp
Version: 2024.5.26
Summary: A feature-rich command-line audio/video downloader
Project-URL: Documentation, https://github.com/yt-dlp/yt-dlp#readme
Project-URL: Repository, https://github.com/yt-dlp/yt-dlp
Project-URL: Tracker, https://github.com/yt-dlp/yt-dlp/issues
Project-URL: Funding, https://github.com/yt-dlp/yt-dlp/blob/master/Collaborators.md#collaborators
Maintainer-email: pukkandan <pukkandan.ytdlp@gmail.com>, Grub4K <contact@grub4k.xyz>, bashonly <bashonly@protonmail.com>, coletdjnz <coletdjnz@protonmail.com>
License: This is free and unencumbered software released into the public domain.
License-File: AUTHORS
License-File: LICENSE
Keywords: sponsorblock,video-downloader,youtube-dl,youtube-dlc,youtube-downloader,yt-dlp
Classifier: Development Status :: 5 - Production/Stable
Classifier: Environment :: Console
Classifier: License :: OSI Approved :: The Unlicense (Unlicense)
Classifier: Operating System :: OS Independent
Classifier: Programming Language :: Python
Classifier: Programming Language :: Python :: 3 :: Only
Classifier: Programming Language :: Python :: 3.8
Classifier: Programming Language :: Python :: 3.9
Classifier: Programming Language :: Python :: 3.10
Classifier: Programming Language :: Python :: 3.11
Classifier: Programming Language :: Python :: 3.12
Classifier: Programming Language :: Python :: Implementation
Classifier: Programming Language :: Python :: Implementation :: CPython
Classifier: Programming Language :: Python :: Implementation :: PyPy
Classifier: Topic :: Multimedia :: Video
Requires-Python: >=3.8
Requires-Dist: brotli; implementation_name == 'cpython'
Requires-Dist: brotlicffi; implementation_name != 'cpython'
Requires-Dist: certifi
Requires-Dist: mutagen
Requires-Dist: pycryptodomex
Requires-Dist: requests<3,>=2.31.0
Requires-Dist: urllib3<3,>=1.26.17
Requires-Dist: websockets>=12.0
Provides-Extra: build
Requires-Dist: build; extra == 'build'
Requires-Dist: hatchling; extra == 'build'
Requires-Dist: pip; extra == 'build'
Requires-Dist: setuptools<70,>=66.1.0; extra == 'build'
Requires-Dist: wheel; extra == 'build'
Provides-Extra: curl-cffi
Requires-Dist: curl-cffi==0.5.10; (implementation_name == 'cpython') and extra == 'curl-cffi'
Provides-Extra: default
Provides-Extra: dev
Requires-Dist: autopep8~=2.0; extra == 'dev'
Requires-Dist: pre-commit; extra == 'dev'
Requires-Dist: pytest~=8.1; extra == 'dev'
Requires-Dist: ruff~=0.4.4; extra == 'dev'
Provides-Extra: py2exe
Requires-Dist: py2exe>=0.12; extra == 'py2exe'
Requires-Dist: requests==2.31.*; extra == 'py2exe'
Provides-Extra: pyinstaller
Requires-Dist: pyinstaller==5.13.2; (sys_platform == 'darwin') and extra == 'pyinstaller'
Requires-Dist: pyinstaller>=6.3; (sys_platform != 'darwin') and extra == 'pyinstaller'
Provides-Extra: secretstorage
Requires-Dist: cffi; extra == 'secretstorage'
Requires-Dist: secretstorage; extra == 'secretstorage'
Provides-Extra: static-analysis
Requires-Dist: autopep8~=2.0; extra == 'static-analysis'
Requires-Dist: ruff~=0.4.4; extra == 'static-analysis'
Provides-Extra: test
Requires-Dist: pytest~=8.1; extra == 'test'
